mformat_ext/__init__.py
mformat_ext/mformat_docx.py
mformat_ext/mformat_odt.py
mformat_ext/py.typed
mformat_ext/reg_extpkg_formats.py
mformat_ext-0.2.2.dist-info/METADATA
mformat_ext-0.2.2.dist-info/WHEEL
mformat_ext-0.2.2.dist-info/top_level.txt
mformat_ext-0.2.2.dist-info/RECORD
