Metadata-Version: 2.4
Name: mformat_ext
Version: 0.2.2
Summary: Uniform way to write simple text extended with DOCX and ODT files
Author: Tom Björkholm
Author-email: Tom Björkholm <klausuler_linnet0q@icloud.com>
License-Expression: MIT
Project-URL: Source code, https://bitbucket.org/tom-bjorkholm/mformat
Classifier: Programming Language :: Python :: 3
Classifier: Operating System :: OS Independent
Requires-Python: >=3.12
Requires-Dist: mformat>=0.2.2
Requires-Dist: python-docx>=1.2.0
Requires-Dist: odfdo>=3.19.0
Requires-Dist: pip>=25.3
Requires-Dist: setuptools>=80.10.2
Requires-Dist: build>=1.4.0
Requires-Dist: wheel>=0.46.3
Dynamic: author
Dynamic: requires-dist
Dynamic: requires-python
